{"learn_index.md":"4bfc7d4a","download_学习类.md":"377d6d43","live_vpn服务.md":"1e0cf413","download_生活类.md":"d9dcf790","live_生活在矿大_一卡通(校园卡银行卡).md":"f538bf92","newstudent_index.md":"11e09c6a","learn_学分认定.md":"d7b4a1de","index.md":"22dff2cd","download_学生工作类.md":"2bb9f13a","preface_statement.md":"32e82e79","learn_课程体系.md":"b1043791","live_住在矿大电.md":"4ca10385","updatelog.md":"658a906a","preface_preface.md":"a1ebd3bf","learn_培养方案基础知识.md":"f23fe9ae","live_住在矿大校园网.md":"1c2a19da","learn_培养方案解读_通识教育选修课.md":"4790e1d8","markdown-examples.md":"12531ebe","preface_index.md":"5de04c92","live_行在矿大校外.md":"1805ff27"}
